{"metadata":{},"options":{"compact":false,"sourceMaps":true,"ast":true,"babelrc":false,"configFile":false,"parserOpts":{"sourceType":"module","sourceFileName":"/home/snr/Desktop/Project/activity/imports/vue/ui/posAgent.vue","plugins":["*","flow","jsx","asyncGenerators","bigInt","classPrivateMethods","classPrivateProperties","classProperties","doExpressions","dynamicImport","exportDefaultFrom","exportExtensions","exportNamespaceFrom","functionBind","functionSent","importMeta","nullishCoalescingOperator","numericSeparator","objectRestSpread","optionalCatchBinding","optionalChaining",["pipelineOperator",{"proposal":"minimal"}],"throwExpressions","dynamicImport",["flow",{}],"asyncGenerators","objectRestSpread","objectRestSpread",["flow",{}],"asyncGenerators"],"allowImportExportEverywhere":true,"allowReturnOutsideFunction":true,"strictMode":false},"sourceFileName":"/home/snr/Desktop/Project/activity/imports/vue/ui/posAgent.vue","filename":"/home/snr/Desktop/Project/activity/imports/vue/ui/posAgent.vue","passPerPreset":false,"envName":"development","cwd":"/home/snr/Desktop/Project/activity","root":"/home/snr/Desktop/Project/activity","plugins":[{"key":"base$0$0","visitor":{"Program":{"enter":[null]},"_exploded":true,"_verified":true},"options":{"generateLetDeclarations":true,"enforceStrictMode":false}},{"key":"transform-meteor-dynamic-import","visitor":{"_exploded":{},"_verified":{},"CallExpression":{"enter":[null]}},"options":{}},{"key":"transform-runtime","visitor":{"CallExpression":{"enter":[null]},"BinaryExpression":{"enter":[null]},"MemberExpression":{"enter":[null],"exit":[null]},"_exploded":true,"_verified":true,"Identifier":{"enter":[null]},"JSXIdentifier":{"enter":[null]}},"options":{}},{"key":"transform-modules-commonjs","visitor":{"Program":{"exit":[null]},"_exploded":true,"_verified":true},"options":{"allowTopLevelThis":true,"strictMode":false,"loose":true}},{"key":"syntax-flow","visitor":{"_exploded":true,"_verified":true},"options":{}},{"key":"syntax-async-generators","visitor":{"_exploded":true,"_verified":true},"options":{}},{"key":"transform-arrow-functions","visitor":{"ArrowFunctionExpression":{"enter":[null]},"_exploded":true,"_verified":true},"options":{}},{"key":"transform-block-scoped-functions","visitor":{"BlockStatement":{"enter":[null]},"SwitchCase":{"enter":[null]},"_exploded":true,"_verified":true},"options":{}},{"key":"transform-block-scoping","visitor":{"VariableDeclaration":{"enter":[null]},"CatchClause":{"enter":[null]},"_exploded":true,"BlockStatement":{"enter":[null]},"SwitchStatement":{"enter":[null]},"Program":{"enter":[null]},"_verified":true,"DoWhileStatement":{"enter":[null]},"ForInStatement":{"enter":[null]},"ForStatement":{"enter":[null]},"WhileStatement":{"enter":[null]},"ForOfStatement":{"enter":[null]}},"options":{}},{"key":"transform-classes","visitor":{"ExportDefaultDeclaration":{"enter":[null]},"ClassDeclaration":{"enter":[null]},"ClassExpression":{"enter":[null]},"_exploded":true,"_verified":true},"options":{"loose":true}},{"key":"transform-computed-properties","visitor":{"ObjectExpression":{"exit":[null]},"_exploded":true,"_verified":true},"options":{"loose":true}},{"key":"transform-destructuring","visitor":{"ExportNamedDeclaration":{"enter":[null]},"CatchClause":{"enter":[null]},"AssignmentExpression":{"enter":[null]},"VariableDeclaration":{"enter":[null]},"_exploded":true,"_verified":true,"ForInStatement":{"enter":[null]},"ForOfStatement":{"enter":[null]}},"options":{}},{"key":"transform-for-of","visitor":{"ForOfStatement":{"enter":[null]},"_exploded":true,"_verified":true},"options":{"loose":true}},{"key":"transform-literals","visitor":{"NumericLiteral":{"enter":[null]},"StringLiteral":{"enter":[null]},"_exploded":true,"_verified":true},"options":{}},{"key":"transform-object-super","visitor":{"ObjectExpression":{"enter":[null]},"_exploded":true,"_verified":true},"options":{}},{"key":"transform-parameters","visitor":{"_exploded":true,"_verified":true,"FunctionDeclaration":{"enter":[null]},"FunctionExpression":{"enter":[null]},"ObjectMethod":{"enter":[null]},"ArrowFunctionExpression":{"enter":[null]},"ClassMethod":{"enter":[null]},"ClassPrivateMethod":{"enter":[null]}},"options":{}},{"key":"transform-shorthand-properties","visitor":{"ObjectMethod":{"enter":[null]},"ObjectProperty":{"enter":[null]},"_exploded":true,"_verified":true},"options":{}},{"key":"transform-spread","visitor":{"ArrayExpression":{"enter":[null]},"CallExpression":{"enter":[null]},"NewExpression":{"enter":[null]},"_exploded":true,"_verified":true},"options":{}},{"key":"transform-sticky-regex","visitor":{"RegExpLiteral":{"enter":[null]},"_exploded":true,"_verified":true},"options":{}},{"key":"transform-template-literals","visitor":{"TaggedTemplateExpression":{"enter":[null]},"TemplateLiteral":{"enter":[null]},"_exploded":true,"_verified":true},"options":{"loose":true}},{"key":"transform-typeof-symbol","visitor":{"UnaryExpression":{"enter":[null]},"_exploded":true,"_verified":true,"BlockStatement":{"enter":[null]},"CatchClause":{"enter":[null]},"DoWhileStatement":{"enter":[null]},"ForInStatement":{"enter":[null]},"ForStatement":{"enter":[null]},"FunctionDeclaration":{"enter":[null]},"FunctionExpression":{"enter":[null]},"Program":{"enter":[null]},"ObjectMethod":{"enter":[null]},"SwitchStatement":{"enter":[null]},"WhileStatement":{"enter":[null]},"ArrowFunctionExpression":{"enter":[null]},"ClassDeclaration":{"enter":[null]},"ClassExpression":{"enter":[null]},"ForOfStatement":{"enter":[null]},"ClassMethod":{"enter":[null]},"ClassPrivateMethod":{"enter":[null]}},"options":{}},{"key":"transform-unicode-regex","visitor":{"RegExpLiteral":{"enter":[null]},"_exploded":true,"_verified":true},"options":{}},{"key":"syntax-object-rest-spread","visitor":{"_exploded":true,"_verified":true},"options":{}},{"key":"proposal-object-rest-spread","visitor":{"_exploded":{},"_verified":{},"VariableDeclarator":{"enter":[null]},"ExportNamedDeclaration":{"enter":[null]},"CatchClause":{"enter":[null]},"AssignmentExpression":{"enter":[null]},"ObjectExpression":{"enter":[null]},"FunctionDeclaration":{"enter":[null]},"FunctionExpression":{"enter":[null]},"ObjectMethod":{"enter":[null]},"ArrowFunctionExpression":{"enter":[null]},"ClassMethod":{"enter":[null]},"ClassPrivateMethod":{"enter":[null]},"ForInStatement":{"enter":[null]},"ForOfStatement":{"enter":[null]}},"options":{}},{"key":"transform-property-literals","visitor":{"ObjectProperty":{"exit":[null]},"_exploded":true,"_verified":true},"options":{}},{"key":"transform-flow-strip-types","visitor":{"_exploded":{},"_verified":{},"Program":{"enter":[null]},"ImportDeclaration":{"enter":[null,null]},"ClassProperty":{"enter":[null]},"ClassPrivateProperty":{"enter":[null]},"AssignmentPattern":{"enter":[null]},"TypeCastExpression":{"enter":[null,null]},"CallExpression":{"enter":[null]},"OptionalCallExpression":{"enter":[null]},"NewExpression":{"enter":[null]},"ImportSpecifier":{"enter":[null]},"ClassDeclaration":{"enter":[null]},"ClassExpression":{"enter":[null]},"FunctionDeclaration":{"enter":[null]},"FunctionExpression":{"enter":[null]},"ObjectMethod":{"enter":[null]},"ArrowFunctionExpression":{"enter":[null]},"ClassMethod":{"enter":[null]},"ClassPrivateMethod":{"enter":[null]},"AnyTypeAnnotation":{"enter":[null]},"ArrayTypeAnnotation":{"enter":[null]},"BooleanTypeAnnotation":{"enter":[null]},"BooleanLiteralTypeAnnotation":{"enter":[null]},"NullLiteralTypeAnnotation":{"enter":[null]},"ClassImplements":{"enter":[null]},"DeclareClass":{"enter":[null]},"DeclareFunction":{"enter":[null]},"DeclareInterface":{"enter":[null]},"DeclareModule":{"enter":[null]},"DeclareModuleExports":{"enter":[null]},"DeclareTypeAlias":{"enter":[null]},"DeclareOpaqueType":{"enter":[null]},"DeclareVariable":{"enter":[null]},"DeclareExportDeclaration":{"enter":[null]},"DeclareExportAllDeclaration":{"enter":[null]},"DeclaredPredicate":{"enter":[null]},"ExistsTypeAnnotation":{"enter":[null]},"FunctionTypeAnnotation":{"enter":[null]},"FunctionTypeParam":{"enter":[null]},"GenericTypeAnnotation":{"enter":[null]},"InferredPredicate":{"enter":[null]},"InterfaceExtends":{"enter":[null]},"InterfaceDeclaration":{"enter":[null]},"InterfaceTypeAnnotation":{"enter":[null]},"IntersectionTypeAnnotation":{"enter":[null]},"MixedTypeAnnotation":{"enter":[null]},"EmptyTypeAnnotation":{"enter":[null]},"NullableTypeAnnotation":{"enter":[null]},"NumberLiteralTypeAnnotation":{"enter":[null]},"NumberTypeAnnotation":{"enter":[null]},"ObjectTypeAnnotation":{"enter":[null]},"ObjectTypeInternalSlot":{"enter":[null]},"ObjectTypeCallProperty":{"enter":[null]},"ObjectTypeIndexer":{"enter":[null]},"ObjectTypeProperty":{"enter":[null]},"ObjectTypeSpreadProperty":{"enter":[null]},"OpaqueType":{"enter":[null]},"QualifiedTypeIdentifier":{"enter":[null]},"StringLiteralTypeAnnotation":{"enter":[null]},"StringTypeAnnotation":{"enter":[null]},"ThisTypeAnnotation":{"enter":[null]},"TupleTypeAnnotation":{"enter":[null]},"TypeofTypeAnnotation":{"enter":[null]},"TypeAlias":{"enter":[null]},"TypeAnnotation":{"enter":[null]},"TypeParameter":{"enter":[null]},"TypeParameterDeclaration":{"enter":[null]},"TypeParameterInstantiation":{"enter":[null]},"UnionTypeAnnotation":{"enter":[null]},"Variance":{"enter":[null]},"VoidTypeAnnotation":{"enter":[null]},"ExportAllDeclaration":{"enter":[null]},"ExportDefaultDeclaration":{"enter":[null]},"ExportNamedDeclaration":{"enter":[null]}},"options":{}},{"key":"transform-exponentiation-operator","visitor":{"AssignmentExpression":{"enter":[null]},"BinaryExpression":{"enter":[null]},"_exploded":true,"_verified":true},"options":{}},{"key":"proposal-async-generator-functions","visitor":{"_exploded":{},"_verified":{},"Program":{"enter":[null]}},"options":{}},{"key":"regenerator-transform","visitor":{"_exploded":true,"_verified":true,"FunctionDeclaration":{"exit":[null]},"FunctionExpression":{"exit":[null]},"ObjectMethod":{"exit":[null]},"ArrowFunctionExpression":{"exit":[null]},"ClassMethod":{"exit":[null]},"ClassPrivateMethod":{"exit":[null]}},"options":{}}],"presets":[],"generatorOpts":{"filename":"/home/snr/Desktop/Project/activity/imports/vue/ui/posAgent.vue","comments":true,"compact":false,"sourceMaps":true,"sourceFileName":"/home/snr/Desktop/Project/activity/imports/vue/ui/posAgent.vue"}},"code":"var compoLang;\nmodule.link(\"../../../both/i18n/lang/elem-label\", {\n  \"default\": function (v) {\n    compoLang = v;\n  }\n}, 0);\nmodule.exportDefault({\n  meteor: {\n    langSession: function () {\n      return Session.get('lang') || \"en\";\n    }\n  },\n  data: function () {\n    return {\n      newLoading: true,\n      langSession: null,\n      posAgentData: [],\n      loading: false,\n      searchData: '',\n      isSearching: false,\n      currentPage: 1,\n      currentSize: 10,\n      count: 0,\n      dialogAddPosAgent: false,\n      dialogUpdatePosAgent: false,\n      posAgentForm: {\n        name: \"\",\n        address: \"\",\n        phoneNumber: \"\",\n        description: \"\",\n        _id: \"\"\n      },\n      rules: {\n        name: [{\n          required: true,\n          message: 'Please input name',\n          trigger: 'blur'\n        }],\n        address: [{\n          required: true,\n          message: 'Please input Address',\n          trigger: 'blur'\n        }]\n      },\n      skip: 0\n    };\n  },\n  watch: {\n    currentSize: function (val) {\n      this.isSearching = true;\n      this.skip = (this.currentPage - 1) * val;\n      this.queryData(this.searchData, this.skip, val + this.skip);\n    },\n    currentPage: function (val) {\n      this.isSearching = true;\n      this.skip = (val - 1) * this.currentSize;\n      this.queryData(this.searchData, this.skip, this.currentSize + this.skip);\n    },\n    searchData: function (val) {\n      this.isSearching = true;\n      this.skip = (this.currentPage - 1) * this.currentSize;\n      this.queryData(val, this.skip, this.currentSize + this.skip);\n    }\n  },\n  methods: {\n    handleSizeChange: function (val) {\n      this.currentSize = val;\n    },\n    handleCurrentChange: function (val) {\n      this.currentPage = val;\n    },\n    queryData: _.debounce(function (val, skip, limit) {\n      var _this = this;\n\n      this.newLoading = true;\n      Meteor.call('queryPosAgent', {\n        q: val,\n        filter: this.filter,\n        options: {\n          skip: skip || 0,\n          limit: limit || 10\n        }\n      }, function (err, result) {\n        if (!err) {\n          _this.posAgentData = result.content;\n          _this.count = result.countPosAgent;\n        }\n\n        _this.isSearching = false;\n        _this.newLoading = false;\n      });\n    }, 300),\n    savePosAgent: function () {\n      var _this2 = this;\n\n      var vm = this;\n      this.$refs[\"posAgentFormAdd\"].validate(function (valid) {\n        if (valid) {\n          var posAgentDoc = {\n            name: vm.posAgentForm.name,\n            address: vm.posAgentForm.address,\n            phoneNumber: vm.posAgentForm.phoneNumber,\n            description: vm.posAgentForm.description,\n            rolesArea: Session.get('area')\n          };\n          Meteor.call(\"insertPosAgent\", posAgentDoc, function (err, result) {\n            if (!err) {\n              vm.$message({\n                duration: 1000,\n                message: _this2.langConfig['saveSuccess'],\n                type: 'success'\n              });\n              vm.dialogAddPosAgent = false;\n              vm.queryData();\n              vm.resetForm();\n              vm.$refs[\"posAgentForm\"].resetFields();\n            } else {\n              vm.$message({\n                duration: 1000,\n                message: err.message,\n                type: 'error'\n              });\n            }\n          });\n        }\n      });\n    },\n    updatePosAgent: function () {\n      var _this3 = this;\n\n      var vm = this;\n      this.$refs[\"posAgentFormUpdate\"].validate(function (valid) {\n        if (valid) {\n          var posAgentDoc = {\n            _id: vm.posAgentForm._id,\n            name: vm.posAgentForm.name,\n            address: vm.posAgentForm.address,\n            phoneNumber: vm.posAgentForm.phoneNumber,\n            description: vm.posAgentForm.description,\n            rolesArea: Session.get('area')\n          };\n          Meteor.call(\"updatePosAgent\", posAgentDoc, function (err, result) {\n            if (!err) {\n              vm.$message({\n                duration: 1000,\n                message: _this3.langConfig['updateSuccess'],\n                type: 'success'\n              });\n              vm.dialogUpdatePosAgent = false;\n              vm.queryData(vm.searchData, vm.skip, vm.currentSize + vm.skip);\n              vm.resetForm();\n              vm.$refs[\"posAgentForm\"].resetFields();\n            } else {\n              vm.$message({\n                duration: 1000,\n                message: _this3.langConfig['updateFail'],\n                type: 'error'\n              });\n            }\n          });\n        }\n      });\n    },\n    removePosAgent: function (index, row, rows) {\n      var _this4 = this;\n\n      var vm = this;\n\n      if (row.transactionNumber <= 0) {\n        this.$confirm(this.langConfig['message'], this.langConfig['warning'], {\n          confirmButtonText: 'OK',\n          cancelButtonText: 'Cancel',\n          type: 'warning'\n        }).then(function () {\n          Meteor.call(\"removePosAgent\", row._id, function (err, result) {\n            if (!err) {\n              rows.splice(index, 1);\n              vm.$message({\n                message: \"\" + row.name + _this4.langConfig['removeSuccess'],\n                type: 'success'\n              });\n            } else {\n              vm.$message({\n                type: 'error',\n                message: _this4.langConfig['removeFail']\n              });\n            }\n          });\n        }).catch(function () {\n          _this4.$message({\n            type: 'info',\n            message: _this4.langConfig['cancel']\n          });\n        });\n      } else {\n        this.$message({\n          type: 'error',\n          message: this.langConfig['messageInovice'] + \" \" + row.transactionNumber\n        });\n      }\n    },\n    findPosAgentById: function (doc) {\n      var vm = this;\n      vm.posAgentForm = {};\n      Meteor.call(\"queryPosAgentById\", doc.row._id, function (err, result) {\n        if (result) {\n          vm.posAgentForm._id = result._id;\n          vm.posAgentForm = result;\n        }\n      });\n    },\n    cancel: function () {\n      this.$message({\n        type: 'info',\n        message: this.langConfig['cancel']\n      });\n    },\n    resetForm: function () {\n      this.posAgentForm._id = \"\";\n\n      if (this.$refs[\"posAgentFormAdd\"]) {\n        this.$refs[\"posAgentFormAdd\"].resetFields();\n      }\n\n      if (this.$refs[\"posAgentFormUpdate\"]) {\n        this.$refs[\"posAgentFormUpdate\"].resetFields();\n      }\n    }\n  },\n  created: function () {\n    this.isSearching = true;\n    this.queryData();\n  },\n  computed: {\n    langConfig: function () {\n      var _this5 = this;\n\n      var data = compoLang.filter(function (config) {\n        return config.lang === _this5.langSession;\n      })[0]['agent'];\n      return data;\n    }\n  }\n});","map":{"version":3,"sources":["/home/snr/Desktop/Project/activity/imports/vue/ui/posAgent.vue"],"names":["compoLang","module","link","v","exportDefault","meteor","langSession","Session","get","data","newLoading","posAgentData","loading","searchData","isSearching","currentPage","currentSize","count","dialogAddPosAgent","dialogUpdatePosAgent","posAgentForm","name","address","phoneNumber","description","_id","rules","required","message","trigger","skip","watch","val","queryData","methods","handleSizeChange","handleCurrentChange","_","debounce","limit","Meteor","call","q","filter","options","err","result","content","countPosAgent","savePosAgent","vm","$refs","validate","valid","posAgentDoc","rolesArea","$message","duration","langConfig","type","resetForm","resetFields","updatePosAgent","removePosAgent","index","row","rows","transactionNumber","$confirm","confirmButtonText","cancelButtonText","then","splice","catch","findPosAgentById","doc","cancel","created","computed","config","lang"],"mappings":"AAAA,IAAIA,SAAJ;AAAcC,MAAM,CAACC,IAAP,CAAY,oCAAZ,EAAiD;AAAA,uBAASC,CAAT,EAAW;AAACH,IAAAA,SAAS,GAACG,CAAV;AAAY;AAAxB,CAAjD,EAA2E,CAA3E;AAAdF,MAAM,CAACG,aAAP,CAmMe;AACXC,EAAAA,MAAM,EAAE;AACJC,IAAAA,WADI,cACU;AACV,aAAOC,OAAO,CAACC,GAAR,CAAY,MAAZ,KAAuB,IAA9B;AACH;AAHG,GADG;AAMXC,EAAAA,IANW,cAMJ;AACH,WAAO;AACHC,MAAAA,UAAU,EAAE,IADT;AAEHJ,MAAAA,WAAW,EAAE,IAFV;AAGHK,MAAAA,YAAY,EAAE,EAHX;AAIHC,MAAAA,OAAO,EAAE,KAJN;AAKHC,MAAAA,UAAU,EAAE,EALT;AAMHC,MAAAA,WAAW,EAAE,KANV;AAOHC,MAAAA,WAAW,EAAE,CAPV;AAQHC,MAAAA,WAAW,EAAE,EARV;AASHC,MAAAA,KAAK,EAAE,CATJ;AAUHC,MAAAA,iBAAiB,EAAE,KAVhB;AAWHC,MAAAA,oBAAoB,EAAE,KAXnB;AAaHC,MAAAA,YAAY,EAAE;AACVC,QAAAA,IAAI,EAAE,EADI;AAEVC,QAAAA,OAAO,EAAE,EAFC;AAGVC,QAAAA,WAAW,EAAE,EAHH;AAIVC,QAAAA,WAAW,EAAE,EAJH;AAKVC,QAAAA,GAAG,EAAE;AALK,OAbX;AAoBHC,MAAAA,KAAK,EAAE;AACHL,QAAAA,IAAI,EAAE,CAAC;AAACM,UAAAA,QAAQ,EAAE,IAAX;AAAiBC,UAAAA,OAAO,EAAE,mBAA1B;AAA+CC,UAAAA,OAAO,EAAE;AAAxD,SAAD,CADH;AAEHP,QAAAA,OAAO,EAAE,CAAC;AAACK,UAAAA,QAAQ,EAAE,IAAX;AAAiBC,UAAAA,OAAO,EAAE,sBAA1B;AAAkDC,UAAAA,OAAO,EAAE;AAA3D,SAAD;AAFN,OApBJ;AAyBHC,MAAAA,IAAI,EAAE;AAzBH,KAAP;AA2BH,GAlCU;AAmCXC,EAAAA,KAAK,EAAE;AACHf,IAAAA,WADG,YACSgB,GADT,EACc;AACb,WAAKlB,WAAL,GAAmB,IAAnB;AACA,WAAKgB,IAAL,GAAY,CAAC,KAAKf,WAAL,GAAmB,CAApB,IAAyBiB,GAArC;AACA,WAAKC,SAAL,CAAe,KAAKpB,UAApB,EAAgC,KAAKiB,IAArC,EAA2CE,GAAG,GAAG,KAAKF,IAAtD;AACH,KALE;AAMHf,IAAAA,WANG,YAMSiB,GANT,EAMc;AACb,WAAKlB,WAAL,GAAmB,IAAnB;AACA,WAAKgB,IAAL,GAAY,CAACE,GAAG,GAAG,CAAP,IAAY,KAAKhB,WAA7B;AACA,WAAKiB,SAAL,CAAe,KAAKpB,UAApB,EAAgC,KAAKiB,IAArC,EAA2C,KAAKd,WAAL,GAAmB,KAAKc,IAAnE;AACH,KAVE;AAWHjB,IAAAA,UAXG,YAWQmB,GAXR,EAWa;AACZ,WAAKlB,WAAL,GAAmB,IAAnB;AACA,WAAKgB,IAAL,GAAY,CAAC,KAAKf,WAAL,GAAmB,CAApB,IAAyB,KAAKC,WAA1C;AACA,WAAKiB,SAAL,CAAeD,GAAf,EAAoB,KAAKF,IAAzB,EAA+B,KAAKd,WAAL,GAAmB,KAAKc,IAAvD;AACH;AAfE,GAnCI;AAoDXI,EAAAA,OAAO,EAAE;AACLC,IAAAA,gBADK,YACYH,GADZ,EACiB;AAClB,WAAKhB,WAAL,GAAmBgB,GAAnB;AACH,KAHI;AAILI,IAAAA,mBAJK,YAIeJ,GAJf,EAIoB;AACrB,WAAKjB,WAAL,GAAmBiB,GAAnB;AACH,KANI;AAOLC,IAAAA,SAAS,EAAEI,CAAC,CAACC,QAAF,CAAW,UAAUN,GAAV,EAAeF,IAAf,EAAqBS,KAArB,EAA4B;AAAA;;AAC9C,WAAK7B,UAAL,GAAkB,IAAlB;AACA8B,MAAAA,MAAM,CAACC,IAAP,CAAY,eAAZ,EAA6B;AACzBC,QAAAA,CAAC,EAAEV,GADsB;AAEzBW,QAAAA,MAAM,EAAE,KAAKA,MAFY;AAGzBC,QAAAA,OAAO,EAAE;AAACd,UAAAA,IAAI,EAAEA,IAAI,IAAI,CAAf;AAAkBS,UAAAA,KAAK,EAAEA,KAAK,IAAI;AAAlC;AAHgB,OAA7B,EAIG,UAACM,GAAD,EAAMC,MAAN,EAAiB;AAChB,YAAI,CAACD,GAAL,EAAU;AACN,UAAA,KAAI,CAAClC,YAAL,GAAoBmC,MAAM,CAACC,OAA3B;AACA,UAAA,KAAI,CAAC9B,KAAL,GAAa6B,MAAM,CAACE,aAApB;AACH;;AACD,QAAA,KAAI,CAAClC,WAAL,GAAmB,KAAnB;AACA,QAAA,KAAI,CAACJ,UAAL,GAAkB,KAAlB;AACH,OAXD;AAYH,KAdU,EAcR,GAdQ,CAPN;AAsBLuC,IAAAA,YAtBK,cAsBU;AAAA;;AACX,UAAIC,EAAE,GAAG,IAAT;AACA,WAAKC,KAAL,CAAW,iBAAX,EAA8BC,QAA9B,CAAuC,UAACC,KAAD,EAAW;AAC9C,YAAIA,KAAJ,EAAW;AACP,cAAIC,WAAW,GAAG;AACdjC,YAAAA,IAAI,EAAE6B,EAAE,CAAC9B,YAAH,CAAgBC,IADR;AAEdC,YAAAA,OAAO,EAAE4B,EAAE,CAAC9B,YAAH,CAAgBE,OAFX;AAGdC,YAAAA,WAAW,EAAE2B,EAAE,CAAC9B,YAAH,CAAgBG,WAHf;AAIdC,YAAAA,WAAW,EAAE0B,EAAE,CAAC9B,YAAH,CAAgBI,WAJf;AAKd+B,YAAAA,SAAS,EAAEhD,OAAO,CAACC,GAAR,CAAY,MAAZ;AALG,WAAlB;AAQAgC,UAAAA,MAAM,CAACC,IAAP,CAAY,gBAAZ,EAA8Ba,WAA9B,EAA2C,UAACT,GAAD,EAAMC,MAAN,EAAiB;AACxD,gBAAI,CAACD,GAAL,EAAU;AACNK,cAAAA,EAAE,CAACM,QAAH,CAAY;AACRC,gBAAAA,QAAQ,EAAE,IADF;AAER7B,gBAAAA,OAAO,EAAE,MAAI,CAAC8B,UAAL,CAAgB,aAAhB,CAFD;AAGRC,gBAAAA,IAAI,EAAE;AAHE,eAAZ;AAKAT,cAAAA,EAAE,CAAChC,iBAAH,GAAuB,KAAvB;AACAgC,cAAAA,EAAE,CAACjB,SAAH;AACAiB,cAAAA,EAAE,CAACU,SAAH;AAEAV,cAAAA,EAAE,CAACC,KAAH,CAAS,cAAT,EAAyBU,WAAzB;AACH,aAXD,MAWO;AACHX,cAAAA,EAAE,CAACM,QAAH,CAAY;AACRC,gBAAAA,QAAQ,EAAE,IADF;AAER7B,gBAAAA,OAAO,EAAEiB,GAAG,CAACjB,OAFL;AAGR+B,gBAAAA,IAAI,EAAE;AAHE,eAAZ;AAKH;AACJ,WAnBD;AAoBH;AACJ,OA/BD;AAiCH,KAzDI;AA0DLG,IAAAA,cA1DK,cA0DY;AAAA;;AACb,UAAIZ,EAAE,GAAG,IAAT;AACA,WAAKC,KAAL,CAAW,oBAAX,EAAiCC,QAAjC,CAA0C,UAACC,KAAD,EAAW;AACjD,YAAIA,KAAJ,EAAW;AACP,cAAIC,WAAW,GAAG;AACd7B,YAAAA,GAAG,EAAEyB,EAAE,CAAC9B,YAAH,CAAgBK,GADP;AAEdJ,YAAAA,IAAI,EAAE6B,EAAE,CAAC9B,YAAH,CAAgBC,IAFR;AAGdC,YAAAA,OAAO,EAAE4B,EAAE,CAAC9B,YAAH,CAAgBE,OAHX;AAIdC,YAAAA,WAAW,EAAE2B,EAAE,CAAC9B,YAAH,CAAgBG,WAJf;AAKdC,YAAAA,WAAW,EAAE0B,EAAE,CAAC9B,YAAH,CAAgBI,WALf;AAMd+B,YAAAA,SAAS,EAAEhD,OAAO,CAACC,GAAR,CAAY,MAAZ;AANG,WAAlB;AASAgC,UAAAA,MAAM,CAACC,IAAP,CAAY,gBAAZ,EAA8Ba,WAA9B,EAA2C,UAACT,GAAD,EAAMC,MAAN,EAAiB;AACxD,gBAAI,CAACD,GAAL,EAAU;AACNK,cAAAA,EAAE,CAACM,QAAH,CAAY;AACRC,gBAAAA,QAAQ,EAAE,IADF;AAER7B,gBAAAA,OAAO,EAAE,MAAI,CAAC8B,UAAL,CAAgB,eAAhB,CAFD;AAGRC,gBAAAA,IAAI,EAAE;AAHE,eAAZ;AAKAT,cAAAA,EAAE,CAAC/B,oBAAH,GAA0B,KAA1B;AACA+B,cAAAA,EAAE,CAACjB,SAAH,CAAaiB,EAAE,CAACrC,UAAhB,EAA4BqC,EAAE,CAACpB,IAA/B,EAAqCoB,EAAE,CAAClC,WAAH,GAAiBkC,EAAE,CAACpB,IAAzD;AACAoB,cAAAA,EAAE,CAACU,SAAH;AAEAV,cAAAA,EAAE,CAACC,KAAH,CAAS,cAAT,EAAyBU,WAAzB;AACH,aAXD,MAWO;AACHX,cAAAA,EAAE,CAACM,QAAH,CAAY;AACRC,gBAAAA,QAAQ,EAAE,IADF;AAER7B,gBAAAA,OAAO,EAAE,MAAI,CAAC8B,UAAL,CAAgB,YAAhB,CAFD;AAGRC,gBAAAA,IAAI,EAAE;AAHE,eAAZ;AAKH;AACJ,WAnBD;AAoBH;AACJ,OAhCD;AAkCH,KA9FI;AA+FLI,IAAAA,cA/FK,YA+FUC,KA/FV,EA+FiBC,GA/FjB,EA+FsBC,IA/FtB,EA+F4B;AAAA;;AAC7B,UAAIhB,EAAE,GAAG,IAAT;;AACA,UAAIe,GAAG,CAACE,iBAAJ,IAAyB,CAA7B,EAAgC;AAC5B,aAAKC,QAAL,CAAc,KAAKV,UAAL,CAAgB,SAAhB,CAAd,EAA0C,KAAKA,UAAL,CAAgB,SAAhB,CAA1C,EAAsE;AAClEW,UAAAA,iBAAiB,EAAE,IAD+C;AAElEC,UAAAA,gBAAgB,EAAE,QAFgD;AAGlEX,UAAAA,IAAI,EAAE;AAH4D,SAAtE,EAIGY,IAJH,CAIQ,YAAM;AACV/B,UAAAA,MAAM,CAACC,IAAP,CAAY,gBAAZ,EAA8BwB,GAAG,CAACxC,GAAlC,EAAuC,UAACoB,GAAD,EAAMC,MAAN,EAAiB;AACpD,gBAAI,CAACD,GAAL,EAAU;AACNqB,cAAAA,IAAI,CAACM,MAAL,CAAYR,KAAZ,EAAmB,CAAnB;AAEAd,cAAAA,EAAE,CAACM,QAAH,CAAY;AACR5B,gBAAAA,OAAO,EAAE,KAAGqC,GAAG,CAAC5C,IAAP,GAAgB,MAAI,CAACqC,UAAL,CAAgB,eAAhB,CADjB;AAERC,gBAAAA,IAAI,EAAE;AAFE,eAAZ;AAMH,aATD,MASO;AACHT,cAAAA,EAAE,CAACM,QAAH,CAAY;AACRG,gBAAAA,IAAI,EAAE,OADE;AAER/B,gBAAAA,OAAO,EAAE,MAAI,CAAC8B,UAAL,CAAgB,YAAhB;AAFD,eAAZ;AAIH;AAEJ,WAjBD;AAmBH,SAxBD,EAwBGe,KAxBH,CAwBS,YAAM;AACX,UAAA,MAAI,CAACjB,QAAL,CAAc;AACVG,YAAAA,IAAI,EAAE,MADI;AAEV/B,YAAAA,OAAO,EAAE,MAAI,CAAC8B,UAAL,CAAgB,QAAhB;AAFC,WAAd;AAIH,SA7BD;AA8BH,OA/BD,MA+BO;AACH,aAAKF,QAAL,CAAc;AACVG,UAAAA,IAAI,EAAE,OADI;AAEV/B,UAAAA,OAAO,EAAE,KAAK8B,UAAL,CAAgB,gBAAhB,IAAoC,GAApC,GAA0CO,GAAG,CAACE;AAF7C,SAAd;AAIH;AACJ,KAtII;AAuILO,IAAAA,gBAvIK,YAuIYC,GAvIZ,EAuIiB;AAClB,UAAIzB,EAAE,GAAG,IAAT;AACAA,MAAAA,EAAE,CAAC9B,YAAH,GAAkB,EAAlB;AAEAoB,MAAAA,MAAM,CAACC,IAAP,CAAY,mBAAZ,EAAiCkC,GAAG,CAACV,GAAJ,CAAQxC,GAAzC,EAA8C,UAACoB,GAAD,EAAMC,MAAN,EAAiB;AAC3D,YAAIA,MAAJ,EAAY;AACRI,UAAAA,EAAE,CAAC9B,YAAH,CAAgBK,GAAhB,GAAsBqB,MAAM,CAACrB,GAA7B;AACAyB,UAAAA,EAAE,CAAC9B,YAAH,GAAkB0B,MAAlB;AACH;AACJ,OALD;AAMH,KAjJI;AAkJL8B,IAAAA,MAlJK,cAkJI;AACL,WAAKpB,QAAL,CAAc;AACVG,QAAAA,IAAI,EAAE,MADI;AAEV/B,QAAAA,OAAO,EAAE,KAAK8B,UAAL,CAAgB,QAAhB;AAFC,OAAd;AAIH,KAvJI;AAwJLE,IAAAA,SAxJK,cAwJO;AACR,WAAKxC,YAAL,CAAkBK,GAAlB,GAAwB,EAAxB;;AACA,UAAI,KAAK0B,KAAL,CAAW,iBAAX,CAAJ,EAAmC;AAC/B,aAAKA,KAAL,CAAW,iBAAX,EAA8BU,WAA9B;AACH;;AAED,UAAI,KAAKV,KAAL,CAAW,oBAAX,CAAJ,EAAsC;AAClC,aAAKA,KAAL,CAAW,oBAAX,EAAiCU,WAAjC;AACH;AAEJ;AAlKI,GApDE;AAwNXgB,EAAAA,OAxNW,cAwND;AACN,SAAK/D,WAAL,GAAmB,IAAnB;AACA,SAAKmB,SAAL;AACH,GA3NU;AA4NX6C,EAAAA,QAAQ,EAAE;AACNpB,IAAAA,UADM,cACO;AAAA;;AACT,UAAIjD,IAAI,GAAGT,SAAS,CAAC2C,MAAV,CAAiB,UAAAoC,MAAM;AAAA,eAAIA,MAAM,CAACC,IAAP,KAAgB,MAAI,CAAC1E,WAAzB;AAAA,OAAvB,EAA6D,CAA7D,EAAgE,OAAhE,CAAX;AACA,aAAOG,IAAP;AACH;AAJK;AA5NC,CAnMf","sourcesContent":["//\n//\n//\n//\n//\n//\n//\n//\n//\n//\n//\n//\n//\n//\n//\n//\n//\n//\n//\n//\n//\n//\n//\n//\n//\n//\n//\n//\n//\n//\n//\n//\n//\n//\n//\n//\n//\n//\n//\n//\n//\n//\n//\n//\n//\n//\n//\n//\n//\n//\n//\n//\n//\n//\n//\n//\n//\n//\n//\n//\n//\n//\n//\n//\n//\n//\n//\n//\n//\n//\n//\n//\n//\n//\n//\n//\n//\n//\n//\n//\n//\n//\n//\n//\n//\n//\n//\n//\n//\n//\n//\n//\n//\n//\n//\n//\n//\n//\n//\n//\n//\n//\n//\n//\n//\n//\n//\n//\n//\n//\n//\n//\n//\n//\n//\n//\n//\n//\n//\n//\n//\n//\n//\n//\n//\n//\n//\n//\n//\n//\n//\n//\n//\n//\n//\n//\n//\n//\n//\n//\n//\n//\n//\n//\n//\n//\n//\n//\n//\n//\n//\n//\n//\n//\n//\n//\n//\n//\n//\n//\n//\n//\n//\n//\n//\n//\n//\n//\n//\n//\n//\n//\n//\n//\n//\n//\n//\n//\n//\n//\n//\n//\n//\n//\n//\n//\n//\n//\n//\n//\n//\n//\n\nimport compoLang from '../../../both/i18n/lang/elem-label'\n\nexport default {\n    meteor: {\n        langSession() {\n            return Session.get('lang') || \"en\";\n        }\n    },\n    data() {\n        return {\n            newLoading: true,\n            langSession: null,\n            posAgentData: [],\n            loading: false,\n            searchData: '',\n            isSearching: false,\n            currentPage: 1,\n            currentSize: 10,\n            count: 0,\n            dialogAddPosAgent: false,\n            dialogUpdatePosAgent: false,\n\n            posAgentForm: {\n                name: \"\",\n                address: \"\",\n                phoneNumber: \"\",\n                description: \"\",\n                _id: \"\"\n            },\n            rules: {\n                name: [{required: true, message: 'Please input name', trigger: 'blur'}],\n                address: [{required: true, message: 'Please input Address', trigger: 'blur'}]\n\n            },\n            skip: 0\n        }\n    },\n    watch: {\n        currentSize(val) {\n            this.isSearching = true;\n            this.skip = (this.currentPage - 1) * val;\n            this.queryData(this.searchData, this.skip, val + this.skip);\n        },\n        currentPage(val) {\n            this.isSearching = true;\n            this.skip = (val - 1) * this.currentSize;\n            this.queryData(this.searchData, this.skip, this.currentSize + this.skip);\n        },\n        searchData(val) {\n            this.isSearching = true;\n            this.skip = (this.currentPage - 1) * this.currentSize;\n            this.queryData(val, this.skip, this.currentSize + this.skip);\n        }\n    },\n    methods: {\n        handleSizeChange(val) {\n            this.currentSize = val;\n        },\n        handleCurrentChange(val) {\n            this.currentPage = val;\n        },\n        queryData: _.debounce(function (val, skip, limit) {\n            this.newLoading = true;\n            Meteor.call('queryPosAgent', {\n                q: val,\n                filter: this.filter,\n                options: {skip: skip || 0, limit: limit || 10}\n            }, (err, result) => {\n                if (!err) {\n                    this.posAgentData = result.content;\n                    this.count = result.countPosAgent;\n                }\n                this.isSearching = false;\n                this.newLoading = false;\n            });\n        }, 300),\n        savePosAgent() {\n            let vm = this;\n            this.$refs[\"posAgentFormAdd\"].validate((valid) => {\n                if (valid) {\n                    let posAgentDoc = {\n                        name: vm.posAgentForm.name,\n                        address: vm.posAgentForm.address,\n                        phoneNumber: vm.posAgentForm.phoneNumber,\n                        description: vm.posAgentForm.description,\n                        rolesArea: Session.get('area')\n                    };\n\n                    Meteor.call(\"insertPosAgent\", posAgentDoc, (err, result) => {\n                        if (!err) {\n                            vm.$message({\n                                duration: 1000,\n                                message: this.langConfig['saveSuccess'],\n                                type: 'success'\n                            });\n                            vm.dialogAddPosAgent = false;\n                            vm.queryData();\n                            vm.resetForm();\n\n                            vm.$refs[\"posAgentForm\"].resetFields();\n                        } else {\n                            vm.$message({\n                                duration: 1000,\n                                message: err.message,\n                                type: 'error'\n                            });\n                        }\n                    })\n                }\n            })\n\n        },\n        updatePosAgent() {\n            let vm = this;\n            this.$refs[\"posAgentFormUpdate\"].validate((valid) => {\n                if (valid) {\n                    let posAgentDoc = {\n                        _id: vm.posAgentForm._id,\n                        name: vm.posAgentForm.name,\n                        address: vm.posAgentForm.address,\n                        phoneNumber: vm.posAgentForm.phoneNumber,\n                        description: vm.posAgentForm.description,\n                        rolesArea: Session.get('area')\n                    };\n\n                    Meteor.call(\"updatePosAgent\", posAgentDoc, (err, result) => {\n                        if (!err) {\n                            vm.$message({\n                                duration: 1000,\n                                message: this.langConfig['updateSuccess'],\n                                type: 'success'\n                            });\n                            vm.dialogUpdatePosAgent = false;\n                            vm.queryData(vm.searchData, vm.skip, vm.currentSize + vm.skip);\n                            vm.resetForm();\n\n                            vm.$refs[\"posAgentForm\"].resetFields();\n                        } else {\n                            vm.$message({\n                                duration: 1000,\n                                message: this.langConfig['updateFail'],\n                                type: 'error'\n                            });\n                        }\n                    })\n                }\n            })\n\n        },\n        removePosAgent(index, row, rows) {\n            let vm = this;\n            if (row.transactionNumber <= 0) {\n                this.$confirm(this.langConfig['message'], this.langConfig['warning'], {\n                    confirmButtonText: 'OK',\n                    cancelButtonText: 'Cancel',\n                    type: 'warning'\n                }).then(() => {\n                    Meteor.call(\"removePosAgent\", row._id, (err, result) => {\n                        if (!err) {\n                            rows.splice(index, 1);\n\n                            vm.$message({\n                                message: `${row.name}` + this.langConfig['removeSuccess'],\n                                type: 'success'\n                            });\n\n\n                        } else {\n                            vm.$message({\n                                type: 'error',\n                                message: this.langConfig['removeFail']\n                            });\n                        }\n\n                    })\n\n                }).catch(() => {\n                    this.$message({\n                        type: 'info',\n                        message: this.langConfig['cancel']\n                    });\n                });\n            } else {\n                this.$message({\n                    type: 'error',\n                    message: this.langConfig['messageInovice'] + \" \" + row.transactionNumber\n                });\n            }\n        },\n        findPosAgentById(doc) {\n            let vm = this;\n            vm.posAgentForm = {};\n\n            Meteor.call(\"queryPosAgentById\", doc.row._id, (err, result) => {\n                if (result) {\n                    vm.posAgentForm._id = result._id;\n                    vm.posAgentForm = result;\n                }\n            })\n        },\n        cancel() {\n            this.$message({\n                type: 'info',\n                message: this.langConfig['cancel']\n            });\n        },\n        resetForm() {\n            this.posAgentForm._id = \"\";\n            if (this.$refs[\"posAgentFormAdd\"]) {\n                this.$refs[\"posAgentFormAdd\"].resetFields();\n            }\n\n            if (this.$refs[\"posAgentFormUpdate\"]) {\n                this.$refs[\"posAgentFormUpdate\"].resetFields();\n            }\n\n        }\n    },\n    created() {\n        this.isSearching = true;\n        this.queryData();\n    },\n    computed: {\n        langConfig() {\n            let data = compoLang.filter(config => config.lang === this.langSession)[0]['agent'];\n            return data;\n        }\n    }\n}\n"]},"sourceType":"script","hash":"1cc11953bbfea4cf8c377cfb10d2995d95b40aab"}
